<annotation>
	<folder>JPEGImages</folder>
	<filename>000268.jpg</filename>
	<path>JPEGImages</path>
	<size>
		<width>500</width>
		<height>330</height>
		<depth>3</depth>
	</size>
	<object>
		<name>ship</name>
		<pose>Unspecified</pose>
		<truncated>0</truncated>
		<difficult>0</difficult>
		<rotated_bndbox>
			<rotated_bbox_cx>88</rotated_bbox_cx>
			<rotated_bbox_cy>36</rotated_bbox_cy>
			<rotated_bbox_w>22</rotated_bbox_w>
			<rotated_bbox_h>7</rotated_bbox_h>
			<rotated_bbox_theta>-0.0</rotated_bbox_theta>
			<x1>77</x1>
			<y1>40</y1>
			<x2>77</x2>
			<y2>33</y2>
			<x3>99</x3>
			<y3>33</y3>
			<x4>99</x4>
			<y4>40</y4>
		</rotated_bndbox>
	</object>
	<object>
		<name>ship</name>
		<pose>Unspecified</pose>
		<truncated>0</truncated>
		<difficult>0</difficult>
		<rotated_bndbox>
			<rotated_bbox_cx>156</rotated_bbox_cx>
			<rotated_bbox_cy>98</rotated_bbox_cy>
			<rotated_bbox_w>8</rotated_bbox_w>
			<rotated_bbox_h>23</rotated_bbox_h>
			<rotated_bbox_theta>68.19859313964844</rotated_bbox_theta>
			<x1>143</x1>
			<y1>99</y1>
			<x2>165</x2>
			<y2>90</y2>
			<x3>168</x3>
			<y3>98</y3>
			<x4>147</x4>
			<y4>106</y4>
		</rotated_bndbox>
	</object>
	<object>
		<name>ship</name>
		<pose>Unspecified</pose>
		<truncated>0</truncated>
		<difficult>0</difficult>
		<rotated_bndbox>
			<rotated_bbox_cx>419</rotated_bbox_cx>
			<rotated_bbox_cy>137</rotated_bbox_cy>
			<rotated_bbox_w>11</rotated_bbox_w>
			<rotated_bbox_h>26</rotated_bbox_h>
			<rotated_bbox_theta>9.462322235107422</rotated_bbox_theta>
			<x1>411</x1>
			<y1>150</y1>
			<x2>416</x2>
			<y2>123</y2>
			<x3>427</x3>
			<y3>125</y3>
			<x4>422</x4>
			<y4>151</y4>
		</rotated_bndbox>
	</object>
	<object>
		<name>ship</name>
		<pose>Unspecified</pose>
		<truncated>0</truncated>
		<difficult>0</difficult>
		<rotated_bndbox>
			<rotated_bbox_cx>391</rotated_bbox_cx>
			<rotated_bbox_cy>192</rotated_bbox_cy>
			<rotated_bbox_w>14</rotated_bbox_w>
			<rotated_bbox_h>6</rotated_bbox_h>
			<rotated_bbox_theta>90.0</rotated_bbox_theta>
			<x1>388</x1>
			<y1>185</y1>
			<x2>394</x2>
			<y2>185</y2>
			<x3>394</x3>
			<y3>199</y3>
			<x4>388</x4>
			<y4>199</y4>
		</rotated_bndbox>
	</object>
	<object>
		<name>ship</name>
		<pose>Unspecified</pose>
		<truncated>0</truncated>
		<difficult>0</difficult>
		<rotated_bndbox>
			<rotated_bbox_cx>375</rotated_bbox_cx>
			<rotated_bbox_cy>288</rotated_bbox_cy>
			<rotated_bbox_w>20</rotated_bbox_w>
			<rotated_bbox_h>6</rotated_bbox_h>
			<rotated_bbox_theta>75.96376037597656</rotated_bbox_theta>
			<x1>370</x1>
			<y1>278</y1>
			<x2>376</x2>
			<y2>277</y2>
			<x3>381</x3>
			<y3>297</y3>
			<x4>375</x4>
			<y4>298</y4>
		</rotated_bndbox>
	</object>
</annotation>