<annotation>
	<folder>JPEGImages</folder>
	<filename>000368.jpg</filename>
	<path>JPEGImages</path>
	<size>
		<width>500</width>
		<height>360</height>
		<depth>3</depth>
	</size>
	<object>
		<name>ship</name>
		<pose>Unspecified</pose>
		<truncated>0</truncated>
		<difficult>0</difficult>
		<rotated_bndbox>
			<rotated_bbox_cx>258</rotated_bbox_cx>
			<rotated_bbox_cy>43</rotated_bbox_cy>
			<rotated_bbox_w>29</rotated_bbox_w>
			<rotated_bbox_h>9</rotated_bbox_h>
			<rotated_bbox_theta>81.8698959350586</rotated_bbox_theta>
			<x1>251</x1>
			<y1>29</y1>
			<x2>260</x2>
			<y2>28</y2>
			<x3>264</x3>
			<y3>57</y3>
			<x4>255</x4>
			<y4>58</y4>
		</rotated_bndbox>
	</object>
	<object>
		<name>ship</name>
		<pose>Unspecified</pose>
		<truncated>0</truncated>
		<difficult>0</difficult>
		<rotated_bndbox>
			<rotated_bbox_cx>359</rotated_bbox_cx>
			<rotated_bbox_cy>163</rotated_bbox_cy>
			<rotated_bbox_w>28</rotated_bbox_w>
			<rotated_bbox_h>10</rotated_bbox_h>
			<rotated_bbox_theta>74.05460357666016</rotated_bbox_theta>
			<x1>350</x1>
			<y1>151</y1>
			<x2>360</x2>
			<y2>148</y2>
			<x3>368</x3>
			<y3>175</y3>
			<x4>357</x4>
			<y4>178</y4>
		</rotated_bndbox>
	</object>
	<object>
		<name>ship</name>
		<pose>Unspecified</pose>
		<truncated>0</truncated>
		<difficult>0</difficult>
		<rotated_bndbox>
			<rotated_bbox_cx>78</rotated_bbox_cx>
			<rotated_bbox_cy>134</rotated_bbox_cy>
			<rotated_bbox_w>36</rotated_bbox_w>
			<rotated_bbox_h>9</rotated_bbox_h>
			<rotated_bbox_theta>79.69515228271484</rotated_bbox_theta>
			<x1>69</x1>
			<y1>117</y1>
			<x2>79</x2>
			<y2>115</y2>
			<x3>86</x3>
			<y3>152</y3>
			<x4>76</x4>
			<y4>153</y4>
		</rotated_bndbox>
	</object>
	<object>
		<name>ship</name>
		<pose>Unspecified</pose>
		<truncated>0</truncated>
		<difficult>0</difficult>
		<rotated_bndbox>
			<rotated_bbox_cx>221</rotated_bbox_cx>
			<rotated_bbox_cy>321</rotated_bbox_cy>
			<rotated_bbox_w>52</rotated_bbox_w>
			<rotated_bbox_h>11</rotated_bbox_h>
			<rotated_bbox_theta>74.05460357666016</rotated_bbox_theta>
			<x1>208</x1>
			<y1>297</y1>
			<x2>219</x2>
			<y2>294</y2>
			<x3>234</x3>
			<y3>345</y3>
			<x4>222</x4>
			<y4>348</y4>
		</rotated_bndbox>
	</object>
	<object>
		<name>ship</name>
		<pose>Unspecified</pose>
		<truncated>0</truncated>
		<difficult>0</difficult>
		<rotated_bndbox>
			<rotated_bbox_cx>43</rotated_bbox_cx>
			<rotated_bbox_cy>293</rotated_bbox_cy>
			<rotated_bbox_w>52</rotated_bbox_w>
			<rotated_bbox_h>7</rotated_bbox_h>
			<rotated_bbox_theta>78.69007110595703</rotated_bbox_theta>
			<x1>34</x1>
			<y1>268</y1>
			<x2>41</x2>
			<y2>267</y2>
			<x3>52</x3>
			<y3>318</y3>
			<x4>44</x4>
			<y4>319</y4>
		</rotated_bndbox>
	</object>
</annotation>