<annotation>
	<folder>JPEGImages</folder>
	<filename>000870.jpg</filename>
	<path>JPEGImages</path>
	<size>
		<width>501</width>
		<height>353</height>
		<depth>3</depth>
	</size>
	<object>
		<name>ship</name>
		<pose>Unspecified</pose>
		<truncated>0</truncated>
		<difficult>0</difficult>
		<rotated_bndbox>
			<rotated_bbox_cx>314</rotated_bbox_cx>
			<rotated_bbox_cy>215</rotated_bbox_cy>
			<rotated_bbox_w>46</rotated_bbox_w>
			<rotated_bbox_h>12</rotated_bbox_h>
			<rotated_bbox_theta>86.8201675415039</rotated_bbox_theta>
			<x1>306</x1>
			<y1>193</y1>
			<x2>319</x2>
			<y2>192</y2>
			<x3>321</x3>
			<y3>238</y3>
			<x4>309</x4>
			<y4>239</y4>
		</rotated_bndbox>
	</object>
	<object>
		<name>ship</name>
		<pose>Unspecified</pose>
		<truncated>0</truncated>
		<difficult>0</difficult>
		<rotated_bndbox>
			<rotated_bbox_cx>482</rotated_bbox_cx>
			<rotated_bbox_cy>192</rotated_bbox_cy>
			<rotated_bbox_w>10</rotated_bbox_w>
			<rotated_bbox_h>50</rotated_bbox_h>
			<rotated_bbox_theta>0.0</rotated_bbox_theta>
			<x1>477</x1>
			<y1>217</y1>
			<x2>477</x2>
			<y2>167</y2>
			<x3>487</x3>
			<y3>167</y3>
			<x4>487</x4>
			<y4>217</y4>
		</rotated_bndbox>
	</object>
</annotation>