<annotation>
	<folder>JPEGImages</folder>
	<filename>001050.jpg</filename>
	<path>JPEGImages</path>
	<size>
		<width>505</width>
		<height>320</height>
		<depth>3</depth>
	</size>
	<object>
		<name>ship</name>
		<pose>Unspecified</pose>
		<truncated>0</truncated>
		<difficult>0</difficult>
		<rotated_bndbox>
			<rotated_bbox_cx>376</rotated_bbox_cx>
			<rotated_bbox_cy>65</rotated_bbox_cy>
			<rotated_bbox_w>13</rotated_bbox_w>
			<rotated_bbox_h>54</rotated_bbox_h>
			<rotated_bbox_theta>87.39744567871094</rotated_bbox_theta>
			<x1>348</x1>
			<y1>60</y1>
			<x2>402</x2>
			<y2>58</y2>
			<x3>403</x3>
			<y3>71</y3>
			<x4>349</x4>
			<y4>73</y4>
		</rotated_bndbox>
	</object>
	<object>
		<name>ship</name>
		<pose>Unspecified</pose>
		<truncated>0</truncated>
		<difficult>0</difficult>
		<rotated_bndbox>
			<rotated_bbox_cx>121</rotated_bbox_cx>
			<rotated_bbox_cy>170</rotated_bbox_cy>
			<rotated_bbox_w>13</rotated_bbox_w>
			<rotated_bbox_h>49</rotated_bbox_h>
			<rotated_bbox_theta>81.8698959350586</rotated_bbox_theta>
			<x1>95</x1>
			<y1>166</y1>
			<x2>144</x2>
			<y2>159</y2>
			<x3>146</x3>
			<y3>173</y3>
			<x4>97</x4>
			<y4>180</y4>
		</rotated_bndbox>
	</object>
</annotation>